xpathfinder/__init__.py
xpathfinder/app.py
xpathfinder/cli.py
xpathfinder/history.py
xpathfinder/llm.py
xpathfinder/xml_utils.py
xpathfinder-0.1.0.dist-info/METADATA
xpathfinder-0.1.0.dist-info/WHEEL
xpathfinder-0.1.0.dist-info/entry_points.txt
xpathfinder-0.1.0.dist-info/top_level.txt
xpathfinder-0.1.0.dist-info/RECORD
