Metadata-Version: 2.4
Name: xpathfinder
Version: 0.1.0
Requires-Dist: lxml
Requires-Dist: PySide6
